sqlitetable
