Metadata-Version: 2.1
Name: sqlitetable
Version: 0.0.2
Summary: Use sqlite just like classes!
Home-page: UNKNOWN
Author: Poiuzy
Author-email: poiuzy-ice@qq.com
Maintainer: Poiuzy
Maintainer-email: poiuzy-ice@qq.com
License: MIT License
Platform: all
License-File: LICENSE
